asgi_request_duration/__init__.py
asgi_request_duration/constants.py
asgi_request_duration/context.py
asgi_request_duration/decorators.py
asgi_request_duration/enums.py
asgi_request_duration/exceptions.py
asgi_request_duration/filters.py
asgi_request_duration/middleware.py
asgi_request_duration-1.0.6.dist-info/LICENSE
asgi_request_duration-1.0.6.dist-info/METADATA
asgi_request_duration-1.0.6.dist-info/WHEEL
asgi_request_duration-1.0.6.dist-info/RECORD
